sdpc/Sdpc.py
sdpc/Sdpc_struct.py
sdpc/__init__.py
sdpc/normalizeStaining.py
sdpc/LINUX/libDecodeSdpc.so
sdpc/LINUX/ffmpeg/libavcodec.so
sdpc/LINUX/ffmpeg/libavcodec.so.58
sdpc/LINUX/ffmpeg/libavcodec.so.58.111.100
sdpc/LINUX/ffmpeg/libavdevice.so
sdpc/LINUX/ffmpeg/libavdevice.so.58
sdpc/LINUX/ffmpeg/libavdevice.so.58.11.102
sdpc/LINUX/ffmpeg/libavfilter.so
sdpc/LINUX/ffmpeg/libavfilter.so.7
sdpc/LINUX/ffmpeg/libavfilter.so.7.87.100
sdpc/LINUX/ffmpeg/libavformat.so
sdpc/LINUX/ffmpeg/libavformat.so.58
sdpc/LINUX/ffmpeg/libavformat.so.58.62.100
sdpc/LINUX/ffmpeg/libavutil.so
sdpc/LINUX/ffmpeg/libavutil.so.56
sdpc/LINUX/ffmpeg/libavutil.so.56.60.100
sdpc/LINUX/ffmpeg/libswresample.so
sdpc/LINUX/ffmpeg/libswresample.so.3
sdpc/LINUX/ffmpeg/libswresample.so.3.8.100
sdpc/LINUX/ffmpeg/libswscale.so
sdpc/LINUX/ffmpeg/libswscale.so.5
sdpc/LINUX/ffmpeg/libswscale.so.5.8.100
sdpc/LINUX/ffmpeg/libx264.so
sdpc/LINUX/ffmpeg/libx264.so.148
sdpc/LINUX/ffmpeg/libx265.so
sdpc/LINUX/ffmpeg/libx265.so.79
sdpc/LINUX/jpeg/libjpeg.a
sdpc/LINUX/jpeg/libjpeg.so
sdpc/LINUX/jpeg/libjpeg.so.8
sdpc/LINUX/jpeg/libjpeg.so.8.2.2
sdpc/LINUX/jpeg/libturbojpeg.a
sdpc/LINUX/jpeg/libturbojpeg.so
sdpc/LINUX/jpeg/libturbojpeg.so.0
sdpc/LINUX/jpeg/libturbojpeg.so.0.2.0
sdpc/WINDOWS/DecodeSdpcDll.lib
sdpc/WINDOWS/avcodec.lib
sdpc/WINDOWS/avdevice.lib
sdpc/WINDOWS/avfilter.lib
sdpc/WINDOWS/avformat.lib
sdpc/WINDOWS/avutil.lib
sdpc/WINDOWS/postproc.lib
sdpc/WINDOWS/swresample.lib
sdpc/WINDOWS/swscale.lib
sdpc/WINDOWS/turbojpeg-static.lib
sdpc/WINDOWS/dll/DecodeSdpcDll.dll
sdpc/WINDOWS/dll/avcodec-58.dll
sdpc/WINDOWS/dll/avdevice-58.dll
sdpc/WINDOWS/dll/avfilter-7.dll
sdpc/WINDOWS/dll/avformat-58.dll
sdpc/WINDOWS/dll/avutil-56.dll
sdpc/WINDOWS/dll/postproc-55.dll
sdpc/WINDOWS/dll/swresample-3.dll
sdpc/WINDOWS/dll/swscale-5.dll
sdpc_for_python-1.0.5.dist-info/METADATA
sdpc_for_python-1.0.5.dist-info/WHEEL
sdpc_for_python-1.0.5.dist-info/top_level.txt
sdpc_for_python-1.0.5.dist-info/RECORD
